<?xml version="1.0" encoding="utf-8"?>
<PathModelComponent xmlns:xsi="http://www.w3.org/2001/XMLSchema-instance" xmlns:xsd="http://www.w3.org/2001/XMLSchema">
  <points>
    <Vector2>
      <x>-3.79629564</x>
      <y>-2.121212</y>
    </Vector2>
    <Vector2>
      <x>0.3114481</x>
      <y>-3.08080769</y>
    </Vector2>
    <Vector2>
      <x>3.25757575</x>
      <y>-1.70033646</y>
    </Vector2>
    <Vector2>
      <x>0.227272347</x>
      <y>2.47474718</y>
    </Vector2>
    <Vector2>
      <x>-4.53703642</x>
      <y>1.76767635</y>
    </Vector2>
    <Vector2>
      <x>-4.048821</x>
      <y>-0.252525181</y>
    </Vector2>
    <Vector2>
      <x>-1.33838344</x>
      <y>-0.151514992</y>
    </Vector2>
    <Vector2>
      <x>-1.11952829</x>
      <y>0.993266</y>
    </Vector2>
  </points>
</PathModelComponent>