<?xml version="1.0" encoding="utf-8"?>
<PathModelComponent xmlns:xsi="http://www.w3.org/2001/XMLSchema-instance" xmlns:xsd="http://www.w3.org/2001/XMLSchema">
  <points>
    <Vector2>
      <x>-3.23233557</x>
      <y>-1.59085441</y>
    </Vector2>
    <Vector2>
      <x>0.890063047</x>
      <y>-2.30915141</y>
    </Vector2>
    <Vector2>
      <x>-2.795112</x>
      <y>1.18864226</y>
    </Vector2>
    <Vector2>
      <x>-1.32728779</x>
      <y>3.343532</y>
    </Vector2>
    <Vector2>
      <x>2.732651</x>
      <y>4.249211</y>
    </Vector2>
    <Vector2>
      <x>-1.04621494</x>
      <y>6.372871</y>
    </Vector2>
    <Vector2>
      <x>-2.20173621</x>
      <y>6.99747753</y>
    </Vector2>
    <Vector2>
      <x>0.921294</x>
      <y>8.777604</y>
    </Vector2>
    <Vector2>
      <x>-1.70205152</x>
      <y>11.026186</y>
    </Vector2>
    <Vector2>
      <x>-3.88817215</x>
      <y>11.3697186</y>
    </Vector2>
    <Vector2>
      <x>1.60835969</x>
      <y>11.8381729</y>
    </Vector2>
  </points>
</PathModelComponent>